granyt_sdk/__init__.py
granyt_sdk/py.typed
granyt_sdk/core/__init__.py
granyt_sdk/core/client.py
granyt_sdk/core/config.py
granyt_sdk/core/transport.py
granyt_sdk/features/__init__.py
granyt_sdk/features/errors/__init__.py
granyt_sdk/features/errors/capture.py
granyt_sdk/features/errors/sanitizer.py
granyt_sdk/features/lineage/__init__.py
granyt_sdk/features/lineage/adapter.py
granyt_sdk/features/metrics/__init__.py
granyt_sdk/features/metrics/core.py
granyt_sdk/features/metrics/adapters/__init__.py
granyt_sdk/features/metrics/adapters/pandas.py
granyt_sdk/features/metrics/adapters/polars.py
granyt_sdk/integrations/__init__.py
granyt_sdk/integrations/airflow/__init__.py
granyt_sdk/integrations/airflow/callbacks.py
granyt_sdk/integrations/airflow/listener.py
granyt_sdk/integrations/airflow/plugin.py
granyt_sdk/integrations/airflow/operator_adapters/__init__.py
granyt_sdk/integrations/airflow/operator_adapters/base.py
granyt_sdk/integrations/airflow/operator_adapters/sql/__init__.py
granyt_sdk/integrations/airflow/operator_adapters/sql/bigquery.py
granyt_sdk/integrations/airflow/operator_adapters/sql/generic.py
granyt_sdk/integrations/airflow/operator_adapters/sql/mysql.py
granyt_sdk/integrations/airflow/operator_adapters/sql/postgres.py
granyt_sdk/integrations/airflow/operator_adapters/sql/redshift.py
granyt_sdk/integrations/airflow/operator_adapters/sql/snowflake.py
granyt_sdk/integrations/airflow/operator_adapters/storage/__init__.py
granyt_sdk/integrations/airflow/operator_adapters/storage/azure.py
granyt_sdk/integrations/airflow/operator_adapters/storage/gcs.py
granyt_sdk/integrations/airflow/operator_adapters/storage/s3.py
granyt_sdk/integrations/airflow/operator_adapters/transform/__init__.py
granyt_sdk/integrations/airflow/operator_adapters/transform/bash.py
granyt_sdk/integrations/airflow/operator_adapters/transform/dbt.py
granyt_sdk/integrations/airflow/operator_adapters/transform/email.py
granyt_sdk/integrations/airflow/operator_adapters/transform/http.py
granyt_sdk-0.2.2.dist-info/licenses/LICENSE
granyt_sdk-0.2.2.dist-info/METADATA
granyt_sdk-0.2.2.dist-info/WHEEL
granyt_sdk-0.2.2.dist-info/entry_points.txt
granyt_sdk-0.2.2.dist-info/top_level.txt
granyt_sdk-0.2.2.dist-info/RECORD
