Metadata-Version: 2.4
Name: granyt-sdk
Version: 0.2.2
Summary: Granyt SDK for Apache Airflow - Automatic lineage tracking and error monitoring
Author-email: Johnny Kessler <johnny@granyt.dev>
Maintainer-email: Johnny Kessler <johnny@granyt.dev>
License: MIT
Project-URL: Homepage, https://github.com/jhkessler/getgranyt
Project-URL: Documentation, https://granyt.dev/docs
Project-URL: Repository, https://github.com/jhkessler/getgranyt
Project-URL: Bug Tracker, https://github.com/jhkessler/getgranyt/issues
Classifier: Development Status :: 4 - Beta
Classifier: Intended Audience :: Developers
Classifier: License :: OSI Approved :: MIT License
Classifier: Operating System :: OS Independent
Classifier: Programming Language :: Python :: 3
Classifier: Programming Language :: Python :: 3.9
Classifier: Programming Language :: Python :: 3.10
Classifier: Programming Language :: Python :: 3.11
Classifier: Programming Language :: Python :: 3.12
Classifier: Framework :: Apache Airflow
Classifier: Framework :: Apache Airflow :: Provider
Requires-Python: >=3.9
License-File: LICENSE
Requires-Dist: apache-airflow>=2.7.0
Requires-Dist: openlineage-python>=1.7.0
Requires-Dist: requests>=2.28.0
Requires-Dist: attrs>=23.0.0
Provides-Extra: dev
Requires-Dist: pytest>=7.4.0; extra == "dev"
Requires-Dist: pytest-mock>=3.12.0; extra == "dev"
Requires-Dist: pytest-cov>=4.1.0; extra == "dev"
Requires-Dist: responses>=0.24.0; extra == "dev"
Requires-Dist: black>=23.0.0; extra == "dev"
Requires-Dist: isort>=5.12.0; extra == "dev"
Requires-Dist: mypy>=1.7.0; extra == "dev"
Requires-Dist: types-requests>=2.31.0; extra == "dev"
Dynamic: license-file
